LICENCE
MANIFEST.in
README.rst
setup.py
Hammertime.egg-info/PKG-INFO
Hammertime.egg-info/SOURCES.txt
Hammertime.egg-info/dependency_links.txt
Hammertime.egg-info/entry_points.txt
Hammertime.egg-info/not-zip-safe
Hammertime.egg-info/requires.txt
Hammertime.egg-info/top_level.txt
hammertime/__init__.py