Metadata-Version: 1.0
Name: Hammertime
Version: 0.2.4
Summary: Time tracking with git.
Home-page: https://github.com/caffeinehit/hammertime
Author: Alen Mujezinovic
Author-email: alen@caffeinehit.com
License: MIT
Keywords: git time tracking
Platform: UNKNOWN
Classifier: Development Status :: 4 - Beta
Classifier: Environment :: Console
Classifier: Intended Audience :: Developers
Classifier: License :: OSI Approved :: MIT License
Classifier: Operating System :: MacOS :: MacOS X
Classifier: Operating System :: POSIX
Classifier: Programming Language :: Python :: 2.6
Classifier: Programming Language :: Python :: 2.7
Classifier: Topic :: Software Development
